digitsclassifier-2.1.0.dist-info/METADATA
digitsclassifier-2.1.0.dist-info/WHEEL
digitsclassifier-2.1.0.dist-info/entry_points.txt
digitsclassifier/__init__.py
digitsclassifier/inference.py
digitsclassifier/models/digit_classifier_model.keras
digitsclassifier-2.1.0.dist-info/RECORD
