Metadata-Version: 2.1
Name: digitsclassifier
Version: 2.1.0
Summary: Library to detect single digits (0-9) in black/white images
Author-Email: Knopf <webmaster@pgn-app.com>
License: MIT
Requires-Python: >=3.11
Requires-Dist: pillow>=11.1.0
Requires-Dist: tensorflow>=2.19.0
Requires-Dist: keras>=3.9.2
